plugin_manage_banyan/__init__.py
plugin_manage_banyan/plugin.py
plugin_manage_banyan-0.0.5.dist-info/METADATA
plugin_manage_banyan-0.0.5.dist-info/WHEEL
plugin_manage_banyan-0.0.5.dist-info/RECORD
