Metadata-Version: 2.3
Name: plugin_manage_banyan
Version: 0.0.5
Summary: 
Author: jybaby1027
Author-email: 18523852976@126.com
Requires-Python: >=3.11, <4.0
Classifier: Programming Language :: Python :: 3
Classifier: Programming Language :: Python :: 3.11
Classifier: Programming Language :: Python :: 3.12
Classifier: Programming Language :: Python :: 3.13
Provides-Extra: jupyter
Requires-Dist: jupyter (>=1.1.0,<2.0.0) ; extra == "jupyter"
Requires-Dist: twitter-plugin-banyan (>=0.0.1,<1.0.2)
